tidier/__init__.py
tidier/cli.py
tidier/core/__init__.py
tidier/core/utils.py
tidier/core/classes/__init__.py
tidier/core/classes/file.py
Tidier-0.5.4.dist-info/LICENSE.txt
Tidier-0.5.4.dist-info/METADATA
Tidier-0.5.4.dist-info/WHEEL
Tidier-0.5.4.dist-info/entry_points.txt
Tidier-0.5.4.dist-info/top_level.txt
Tidier-0.5.4.dist-info/RECORD
