Metadata-Version: 2.1
Name: Tidier
Version: 0.5.4
Summary: A tool for organizing files
Home-page: https://github.com/itsamirhn/Tidier
Download-URL: https://github.com/itsamirhn/Tidier/archive/refs/tags/v0.5.4.tar.gz
Author: AmirMohammad Hosseini Nasab
Author-email: awmirhn@gmail.com
License: MIT License        
Requires-Python: >=3
License-File: LICENSE.txt
Requires-Dist: Click
Requires-Dist: jdatetime
Requires-Dist: pathlib
